<?xml version="1.0" encoding="UTF-8"?><record_update table="sp_instance">
    <sp_instance action="INSERT_OR_UPDATE">
        <active>true</active>
        <class_name/>
        <color>default</color>
        <css/>
        <glyph/>
        <id/>
        <order>1</order>
        <roles/>
        <short_description/>
        <size>md</size>
        <sp_column display_value="1">da68ad2fdb40101092ddcd3f299619b8</sp_column>
        <sp_widget display_value="Idea Sidebar">630ded27db80101092ddcd3f29961957</sp_widget>
        <sys_class_name>sp_instance</sys_class_name>
        <sys_created_by>nithin</sys_created_by>
        <sys_created_on>2020-04-14 12:06:57</sys_created_on>
        <sys_id>668d69e7db80101092ddcd3f2996194c</sys_id>
        <sys_mod_count>0</sys_mod_count>
        <sys_name/>
        <sys_package display_value="Idea Portal" source="x_snc_idea_portal">4da17b35db9fc70094407f6bbf961985</sys_package>
        <sys_policy/>
        <sys_scope display_value="Idea Portal">4da17b35db9fc70094407f6bbf961985</sys_scope>
        <sys_update_name>sp_instance_668d69e7db80101092ddcd3f2996194c</sys_update_name>
        <sys_updated_by>nithin</sys_updated_by>
        <sys_updated_on>2020-04-14 12:06:57</sys_updated_on>
        <title/>
        <url/>
        <widget_parameters/>
    </sp_instance>
    <sys_translated_text action="delete_multiple" query="documentkey=668d69e7db80101092ddcd3f2996194c"/>
</record_update>
